osonkod/__init__.py
osonkod/_init_.py
osonkod-0.1.0.dist-info/LICENSE
osonkod-0.1.0.dist-info/METADATA
osonkod-0.1.0.dist-info/WHEEL
osonkod-0.1.0.dist-info/top_level.txt
osonkod-0.1.0.dist-info/RECORD
